Proyecto_1_VS/src/design/seg7_display.sv
// =============================================================================
// Módulo: seg7_display
// Descripción: Codifica 4 bits binarios para mostrarlos en un display de
//              7 segmentos en formato hexadecimal (0-F).
//              Display de ÁNODO COMÚN → segmento encendido con '0' (activo bajo).
//
// Distribución de segmentos en seg7[6:0]:
//        seg7[6] = g (segmento central)
//        seg7[5] = f (segmento superior izquierdo)
//        seg7[4] = e (segmento inferior izquierdo)
//        seg7[3] = d (segmento inferior)
//        seg7[2] = c (segmento inferior derecho)
//        seg7[1] = b (segmento superior derecho)
//        seg7[0] = a (segmento superior)
//
//        --a--
//       f     b
//        --g--
//       e     c
//        --d--
//
// Entradas:
//   data [3:0] - Palabra corregida en binario (valor 0 a 15)
// Salidas:
//   seg7 [6:0] - Señales a los 7 segmentos (activo bajo para ánodo común)
// =============================================================================

module seg7_display (
    input  wire [3:0] data,   // Palabra de 4 bits a mostrar (0–15)
    output reg  [6:0] seg7    // {g, f, e, d, c, b, a} — activo bajo
);

reg [6:0] seg_int;

    // Tabla de verdad para display ánodo común (0 = segmento encendido)
    //                      gfedcba
    always @(*) begin
        case (data) // 
            4'h0: seg_int = 7'b1000000; // 0
            4'h1: seg_int = 7'b1111001; // 1
            4'h2: seg_int = 7'b0100100; // 2
            4'h3: seg_int = 7'b0110000; // 3
            4'h4: seg_int = 7'b0011001; // 4
            4'h5: seg_int = 7'b0010010; // 5
            4'h6: seg_int = 7'b0000010; // 6
            4'h7: seg_int = 7'b1111000; // 7
            4'h8: seg_int = 7'b0000000; // 8
            4'h9: seg_int = 7'b0010000; // 9
            4'hA: seg_int = 7'b0001000; // A
            4'hB: seg_int = 7'b0000011; // b
            4'hC: seg_int = 7'b1000110; // C
            4'hD: seg_int = 7'b0100001; // d
            4'hE: seg_int = 7'b0000110; // E
            4'hF: seg_int = 7'b0001110; // F
            default: seg_int = 7'b1111111; // Apagado
        endcase
    end

    assign seg7 = ~seg_int;

endmodule

Proyecto_1_VS/src/design/led_display.sv
// =============================================================================
// Módulo: led_display
// Descripción: Despliega la palabra corregida de 4 bits en los LEDs de la FPGA.
//              Los LEDs de la TangNano son activos en BAJO (1 = apagado).
// Entradas:
//   data [3:0] - Palabra corregida proveniente del módulo corrector
// Salidas:
//   leds [3:0] - Conexión directa a los 4 LEDs de la FPGA
// =============================================================================

module led_display (
    input  wire [3:0] data,   // Palabra corregida (d4 d3 d2 d1)
    output wire [3:0] led    // LEDs de la FPGA (activo en BAJO)
);

    // Asignación directa: cada bit de data enciende su LED correspondiente
    assign led = ~data;

endmodule

Proyecto_1_VS/src/design/corrector.sv
module corrector (
    input  wire [6:0] in,     // palabra recibida
    input  wire [2:0] syn,    // síndrome
    output wire [3:0] data    // datos corregidos
);

// -------- corrección --------
wire [6:0] corr;

assign corr[0] = (syn == 3'b001) ? ~in[0] : in[0];
assign corr[1] = (syn == 3'b010) ? ~in[1] : in[1];
assign corr[2] = (syn == 3'b011) ? ~in[2] : in[2];
assign corr[3] = (syn == 3'b100) ? ~in[3] : in[3];
assign corr[4] = (syn == 3'b101) ? ~in[4] : in[4];
assign corr[5] = (syn == 3'b110) ? ~in[5] : in[5];
assign corr[6] = (syn == 3'b111) ? ~in[6] : in[6];

// -------- extracción de datos --------
// posiciones: d1=3, d2=5, d3=6, d4=7

assign data[0] = corr[2]; // d1
assign data[1] = corr[4]; // d2
assign data[2] = corr[5]; // d3
assign data[3] = corr[6]; // d4

endmodule

Proyecto_1_VS/src/design/decodificador.sv
module decodificador (
    input  wire [6:0] in,     // palabra recibida
    output wire [2:0] err     // síndrome (000 = no error)
);

// Parity checks (Hamming)
assign err[0] = in[0] ^ in[2] ^ in[4] ^ in[6]; // p1
assign err[1] = in[1] ^ in[2] ^ in[5] ^ in[6]; // p2
assign err[2] = in[3] ^ in[4] ^ in[5] ^ in[6]; // p3

endmodule

Proyecto_1_VS/src/design/receptor.sv
module receptor (
    input  wire [6:0] in,      // 7-bit entrada (switches/jumpers)
    output wire [3:0] led,    // LEDs (datos corregidos)
    output wire [6:0] seg7,
    output wire [3:0] palabra, 
    output wire [2:0] err    // display 7 segmentos
);

// -------- señales internas --------
//wire [6:0] in = ~in_ext;  // palabra recibida (puede ser in_ext o una versión corregida)
wire [2:0] syn;
wire [3:0] data_corr;

// -------- DECODIFICADOR --------
decodificador dec (
    .in(in),
    .err(syn)
);

// -------- CORRECTOR --------
corrector cor (
    .in(in),
    .syn(syn),
    .data(data_corr)
);

// -------- LED DISPLAY --------
led_display led_disp (
    .data(data_corr),
    .led(led)
);

// -------- 7-SEG DISPLAY --------
seg7_display seg_disp (
    .data(data_corr),
    .seg7(seg7)
);

// -------- salida de error --------
assign err = syn;
assign palabra = data_corr;

endmodule

Proyecto_1_VS/src/sim/receptor_tb.sv
`timescale 1ns/1ps

module receptor_tb;

reg  [6:0] in;
wire [3:0] led;
wire [6:0] seg7;
wire [3:0] palabra;
wire [2:0] err;

// Instantiate your receptor module
receptor uut (
    .in(in),
    .led(led),
    .seg7(seg7),
    .palabra(palabra),
    .err(err)
);

// Helper task
task show;
    begin
        $display("in=%b | err=%b | palabra=%b | led=%b | seg7=%b",
                  in, err, palabra, led, seg7);
    end
endtask;

integer i;

initial begin
    $dumpfile("receptor_tb.vcd");
    $dumpvars(0, receptor_tb);

    // -----------------------------
    // Test 1: No error
    in = 7'b0000000;
    #10 show();

    // -----------------------------
    // Test 2: Single-bit errors
    for (i = 0; i < 7; i = i + 1) begin
        in = 7'b0000000 ^ (7'b0000001 << i);
        #10 show();
    end

    // -----------------------------
    // Test 3: Random value
    in = 7'b1011010;
    #10 show();

    // -----------------------------
    // Test 4: All ones
    in = 7'b1111111;
    #10 show();


    in = 7'b1101101;
    #10 show();

    $finish;
end

endmodule

Proyecto_1_VS/src/build/receptor_tb.vcd
$date
	Tue Apr 14 20:09:59 2026
$end
$version
	Icarus Verilog
$end
$timescale
	1ps
$end
$scope module receptor_tb $end
$var wire 7 ! seg7 [6:0] $end
$var wire 4 " palabra [3:0] $end
$var wire 4 # led [3:0] $end
$var wire 3 $ err [2:0] $end
$var reg 7 % in [6:0] $end
$var integer 32 & i [31:0] $end
$scope module uut $end
$var wire 3 ' err [2:0] $end
$var wire 7 ( in [6:0] $end
$var wire 4 ) palabra [3:0] $end
$var wire 3 * syn [2:0] $end
$var wire 7 + seg7 [6:0] $end
$var wire 4 , led [3:0] $end
$var wire 4 - data_corr [3:0] $end
$scope module cor $end
$var wire 7 . in [6:0] $end
$var wire 3 / syn [2:0] $end
$var wire 4 0 data [3:0] $end
$var wire 7 1 corr [6:0] $end
$upscope $end
$scope module dec $end
$var wire 7 2 in [6:0] $end
$var wire 3 3 err [2:0] $end
$upscope $end
$scope module led_disp $end
$var wire 4 4 data [3:0] $end
$var wire 4 5 led [3:0] $end
$upscope $end
$scope module seg_disp $end
$var wire 4 6 data [3:0] $end
$var wire 7 7 seg7 [6:0] $end
$var reg 7 8 seg_int [6:0] $end
$upscope $end
$upscope $end
$scope task show $end
$upscope $end
$upscope $end
$enddefinitions $end
$comment Show the parameter values. $end
$dumpall
$end
#0
$dumpvars
b1000000 8
b111111 7
b0 6
b1111 5
b0 4
b0 3
b0 2
b0 1
b0 0
b0 /
b0 .
b0 -
b1111 ,
b111111 +
b0 *
b0 )
b0 (
b0 '
bx &
b0 %
b0 $
b1111 #
b0 "
b111111 !
$end
#10000
b1 $
b1 '
b1 *
b1 /
b1 3
b0 1
b1 %
b1 (
b1 .
b1 2
b0 &
#20000
b10 $
b10 '
b10 *
b10 /
b10 3
b0 1
b10 %
b10 (
b10 .
b10 2
b1 &
#30000
b111111 !
b111111 +
b111111 7
b1111 #
b1111 ,
b1111 5
b1000000 8
b11 $
b11 '
b11 *
b11 /
b11 3
b0 "
b0 )
b0 -
b0 0
b0 4
b0 6
b0 1
b100 %
b100 (
b100 .
b100 2
b10 &
#40000
b111111 !
b111111 +
b111111 7
b1111 #
b1111 ,
b1111 5
b1000000 8
b0 "
b0 )
b0 -
b0 0
b0 4
b0 6
b100 $
b100 '
b100 *
b100 /
b100 3
b0 1
b1000 %
b1000 (
b1000 .
b1000 2
b11 &
#50000
b111111 !
b111111 +
b111111 7
b1111 #
b1111 ,
b1111 5
b1000000 8
b0 "
b0 )
b0 -
b0 0
b0 4
b0 6
b101 $
b101 '
b101 *
b101 /
b101 3
b0 1
b10000 %
b10000 (
b10000 .
b10000 2
b100 &
#60000
b111111 !
b111111 +
b111111 7
b1111 #
b1111 ,
b1111 5
b1000000 8
b0 "
b0 )
b0 -
b0 0
b0 4
b0 6
b110 $
b110 '
b110 *
b110 /
b110 3
b0 1
b100000 %
b100000 (
b100000 .
b100000 2
b101 &
#70000
b111111 !
b111111 +
b111111 7
b1111 #
b1111 ,
b1111 5
b1000000 8
b0 "
b0 )
b0 -
b0 0
b0 4
b0 6
b0 1
b111 $
b111 '
b111 *
b111 /
b111 3
b1000000 %
b1000000 (
b1000000 .
b1000000 2
b110 &
#80000
b1110111 !
b1110111 +
b1110111 7
b101 #
b101 ,
b101 5
b1000 8
b1010 "
b1010 )
b1010 -
b1010 0
b1010 4
b1010 6
b100 $
b100 '
b100 *
b100 /
b100 3
b1010010 1
b1011010 %
b1011010 (
b1011010 .
b1011010 2
b111 &
#90000
b1110001 !
b1110001 +
b1110001 7
b0 #
b0 ,
b0 5
b1110 8
b1111 "
b1111 )
b1111 -
b1111 0
b1111 4
b1111 6
b0 $
b0 '
b0 *
b0 /
b0 3
b1111111 1
b1111111 %
b1111111 (
b1111111 .
b1111111 2
#100000
b1101101 !
b1101101 +
b1101101 7
b1010 #
b1010 ,
b1010 5
b10010 8
b101 "
b101 )
b101 -
b101 0
b101 4
b101 6
b111 $
b111 '
b111 *
b111 /
b111 3
b101101 1
b1101101 %
b1101101 (
b1101101 .
b1101101 2
